neuronpedia_inference_client/__init__.py
neuronpedia_inference_client/api/__init__.py
neuronpedia_inference_client/api/default_api.py
neuronpedia_inference_client/api_client.py
neuronpedia_inference_client/api_response.py
neuronpedia_inference_client/configuration.py
neuronpedia_inference_client/exceptions.py
neuronpedia_inference_client/models/__init__.py
neuronpedia_inference_client/models/activation_all_post200_response.py
neuronpedia_inference_client/models/activation_all_post200_response_activations_inner.py
neuronpedia_inference_client/models/activation_all_post_request.py
neuronpedia_inference_client/models/activation_single_post200_response.py
neuronpedia_inference_client/models/activation_single_post200_response_activation.py
neuronpedia_inference_client/models/activation_single_post_request.py
neuronpedia_inference_client/models/activation_topk_by_token_post200_response.py
neuronpedia_inference_client/models/activation_topk_by_token_post200_response_results_inner.py
neuronpedia_inference_client/models/activation_topk_by_token_post200_response_results_inner_top_features_inner.py
neuronpedia_inference_client/models/activation_topk_by_token_post_request.py
neuronpedia_inference_client/models/np_feature.py
neuronpedia_inference_client/models/np_steer_chat_message.py
neuronpedia_inference_client/models/np_steer_chat_result.py
neuronpedia_inference_client/models/np_steer_completion_response_inner.py
neuronpedia_inference_client/models/np_steer_feature.py
neuronpedia_inference_client/models/np_steer_method.py
neuronpedia_inference_client/models/np_steer_type.py
neuronpedia_inference_client/models/np_steer_vector.py
neuronpedia_inference_client/models/steer_completion_chat_post200_response.py
neuronpedia_inference_client/models/steer_completion_chat_post_request.py
neuronpedia_inference_client/models/steer_completion_post200_response.py
neuronpedia_inference_client/models/steer_completion_request.py
neuronpedia_inference_client/models/tokenize_post200_response.py
neuronpedia_inference_client-1.2.0.dist-info/METADATA
neuronpedia_inference_client-1.2.0.dist-info/WHEEL
neuronpedia_inference_client-1.2.0.dist-info/RECORD
